{
  "salt": "s4ZPbUupgH0xLQJ8gppm5w==",
  "wrapped": {
    "data_aes_key": {
      "nonce": "lstLrK4a6DIk/mRG",
      "ct": "O5lcJm12z1iAfpTJEYbU6CE2kiDX4tC59kF9IGe823A=",
      "tag": "L/BdgGx80RjLRvQCBZfQyA=="
    },
    "data_iv": {
      "nonce": "Zd9Hrg+cDafT8Uiv",
      "ct": "pOfVwMkqwN97JdVZeJhnOw==",
      "tag": "6EjQigL/fxNwW+wbRX2CrA=="
    },
    "chacha_key": {
      "nonce": "hZImQar03O2cd4u7",
      "ct": "tc6+t9OBn+E5DxQminDsZ1qlDLhKP21uZFZGOQlfv0M=",
      "tag": "YHfGIEtlwOFAdTsIf+aCxQ=="
    },
    "blowfish_key": {
      "nonce": "EuJnRVXqI1/ZKY/f",
      "ct": "w+woBjmRRcaQysWThLSvLwygMPNVGcw8043cvKFgBp9IFuqbJE+OK+Zf69A=",
      "tag": "hCkJsAtrDmY5zge0mccK6w=="
    },
    "rc4_key": {
      "nonce": "W7D7z2x5LNFcoYEU",
      "ct": "h7t0Y/lGtVnzfSy+mWV24PoKdblrwAq5fGkdBqltntnhxQTVReF9gxamc2Q=",
      "tag": "g+3qC7kq3Jpa/7MTfTIF7g=="
    }
  }
}